bio2zarr/__init__.py
bio2zarr/__main__.py
bio2zarr/_version.py
bio2zarr/cli.py
bio2zarr/constants.py
bio2zarr/core.py
bio2zarr/plink.py
bio2zarr/provenance.py
bio2zarr/tskit.py
bio2zarr/typing.py
bio2zarr/vcf.py
bio2zarr/vcf_utils.py
bio2zarr/vcz.py
bio2zarr/vcz_verification.py
bio2zarr/zarr_utils.py
bio2zarr-0.1.6.dist-info/licenses/LICENSE
bio2zarr-0.1.6.dist-info/METADATA
bio2zarr-0.1.6.dist-info/WHEEL
bio2zarr-0.1.6.dist-info/entry_points.txt
bio2zarr-0.1.6.dist-info/top_level.txt
bio2zarr-0.1.6.dist-info/RECORD
