Metadata-Version: 2.4
Name: bio2zarr
Version: 0.1.6
Summary: Convert bioinformatics data to Zarr
Author-email: sgkit Developers <project@sgkit.dev>
License:                                  Apache License
Project-URL: repository, https://github.com/sgkit-dev/bio2zarr
Project-URL: documentation, https://sgkit-dev.github.io/bio2zarr/
Classifier: Development Status :: 4 - Beta
Classifier: License :: OSI Approved :: Apache Software License
Classifier: Operating System :: POSIX
Classifier: Operating System :: POSIX :: Linux
Classifier: Operating System :: MacOS
Classifier: Operating System :: MacOS :: MacOS X
Classifier: Intended Audience :: Science/Research
Classifier: Programming Language :: Python
Classifier: Programming Language :: Python :: 3
Classifier: Programming Language :: Python :: 3.10
Classifier: Programming Language :: Python :: 3.11
Classifier: Programming Language :: Python :: 3.12
Classifier: Topic :: Scientific/Engineering
Requires-Python: >=3.10
License-File: LICENSE
Requires-Dist: numpy>=1.26
Requires-Dist: zarr<3,>=2.17
Requires-Dist: numcodecs[msgpack]!=0.14.0,!=0.14.1,<0.16
Requires-Dist: tabulate
Requires-Dist: tqdm
Requires-Dist: humanfriendly
Requires-Dist: coloredlogs
Requires-Dist: click
Requires-Dist: pandas
Provides-Extra: dev
Requires-Dist: click>=8.2.0; extra == "dev"
Requires-Dist: hypothesis-vcf; extra == "dev"
Requires-Dist: msprime; extra == "dev"
Requires-Dist: pysam; extra == "dev"
Requires-Dist: pytest; extra == "dev"
Requires-Dist: pytest-coverage; extra == "dev"
Requires-Dist: pytest-xdist; extra == "dev"
Requires-Dist: sgkit>=0.8.0; extra == "dev"
Requires-Dist: tqdm; extra == "dev"
Requires-Dist: tskit>=0.6.4; extra == "dev"
Requires-Dist: bed_reader; extra == "dev"
Requires-Dist: cyvcf2; extra == "dev"
Provides-Extra: tskit
Requires-Dist: tskit>=0.6.4; extra == "tskit"
Provides-Extra: vcf
Requires-Dist: cyvcf2; extra == "vcf"
Provides-Extra: all
Requires-Dist: tskit>=0.6.4; extra == "all"
Requires-Dist: cyvcf2; extra == "all"
Dynamic: license-file
